MANIFEST.in
README.md
setup.py
pierogi/__init__.py
pierogi/pierogi.py
pierogi.egg-info/PKG-INFO
pierogi.egg-info/SOURCES.txt
pierogi.egg-info/dependency_links.txt
pierogi.egg-info/top_level.txt
pierogi/__pycache__/__init__.cpython-37.pyc
pierogi/__pycache__/pierogi.cpython-37.pyc
pierogi/utils/__init__.py
pierogi/utils/websocket.py
pierogi/utils/websocket_client.html
pierogi/utils/__pycache__/__init__.cpython-37.pyc
pierogi/utils/__pycache__/websocket.cpython-37.pyc
pierogi/webapp/package-lock.json
pierogi/webapp/pierogi.html
pierogi/webapp/node_modules/chart.js/LICENSE.md
pierogi/webapp/node_modules/chart.js/README.md
pierogi/webapp/node_modules/chart.js/bower.json
pierogi/webapp/node_modules/chart.js/composer.json
pierogi/webapp/node_modules/chart.js/package.json
pierogi/webapp/node_modules/chart.js/dist/Chart.bundle.js
pierogi/webapp/node_modules/chart.js/dist/Chart.bundle.min.js
pierogi/webapp/node_modules/chart.js/dist/Chart.css
pierogi/webapp/node_modules/chart.js/dist/Chart.js
pierogi/webapp/node_modules/chart.js/dist/Chart.min.css
pierogi/webapp/node_modules/chart.js/dist/Chart.min.js
pierogi/webapp/node_modules/chartjs-color/CHANGELOG.md
pierogi/webapp/node_modules/chartjs-color/LICENSE
pierogi/webapp/node_modules/chartjs-color/README.md
pierogi/webapp/node_modules/chartjs-color/index.js
pierogi/webapp/node_modules/chartjs-color/package.json
pierogi/webapp/node_modules/chartjs-color-string/.travis.yml
pierogi/webapp/node_modules/chartjs-color-string/CHANGELOG.md
pierogi/webapp/node_modules/chartjs-color-string/LICENSE
pierogi/webapp/node_modules/chartjs-color-string/README.md
pierogi/webapp/node_modules/chartjs-color-string/color-string.js
pierogi/webapp/node_modules/chartjs-color-string/package.json
pierogi/webapp/node_modules/chartjs-color-string/test/basic.js
pierogi/webapp/node_modules/color-convert/.travis.yml
pierogi/webapp/node_modules/color-convert/CHANGELOG.md
pierogi/webapp/node_modules/color-convert/LICENSE
pierogi/webapp/node_modules/color-convert/README.md
pierogi/webapp/node_modules/color-convert/component.json
