Metadata-Version: 1.2
Name: pierogi
Version: 0.2.0
Summary: Visualiwze and tweak your Machine Learning model.
Home-page: https://github.com/nalepae/pierogi
Author: Manu NALEPA
Author-email: nalepae@gmail.com
License: BSD
Platform: UNKNOWN
Requires-Python: >=3.5
